blog/__init__.py
blog/admin.py
blog/apps.py
blog/config.py
blog/context_processors.py
blog/models.py
blog/tests.py
blog/urls.py
blog/utils.py
blog/views.py
blog/migrations/0001_initial.py
blog/migrations/0002_tag_slug.py
blog/migrations/0003_populate_slug.py
blog/migrations/0004_unique_slug.py
blog/migrations/__init__.py
blog/templates/blog/blog_detail.html
blog/templates/blog/blog_form.html
blog/templates/blog/blog_list.html
blog/templatetags/__init__.py
blog/templatetags/hexia_blog_tags.py
hexia_blog-1.0.12.dist-info/LICENSE
hexia_blog-1.0.12.dist-info/METADATA
hexia_blog-1.0.12.dist-info/WHEEL
hexia_blog-1.0.12.dist-info/top_level.txt
hexia_blog-1.0.12.dist-info/RECORD
