Metadata-Version: 2.1
Name: hexia-blog
Version: 1.0.12
Summary: A simple Django Blog app.
Home-page: https://github.com/HenryMehta/hexia-blog
Author: Henry Mehta
Author-email: hjsmehta@gmail.com
License: MIT License
Keywords: django blog app
Platform: UNKNOWN
Classifier: Environment :: Web Environment
Classifier: Framework :: Django
Classifier: Framework :: Django :: 2.0
Classifier: Intended Audience :: Developers
Classifier: License :: OSI Approved :: MIT License
Classifier: Operating System :: OS Independent
Classifier: Programming Language :: Python
Classifier: Programming Language :: Python :: 3.6
Classifier: Topic :: Internet :: WWW/HTTP
Classifier: Topic :: Internet :: WWW/HTTP :: Dynamic Content
Requires-Python: >=3
Requires-Dist: django-ckeditor
